pyphantom_image/__init__.py
pyphantom_image/imagetools.c
pyphantom_image/imagetools.cpython-313-darwin.so
pyphantom_image/imagetools.pyi
pyphantom_image/imagetools.pyx
pyphantom_image-1.0.0.dist-info/licenses/LICENSE
pyphantom_image-1.0.0.dist-info/METADATA
pyphantom_image-1.0.0.dist-info/WHEEL
pyphantom_image-1.0.0.dist-info/top_level.txt
pyphantom_image-1.0.0.dist-info/RECORD
