Metadata-Version: 2.4
Name: pyphantom_image
Version: 1.0.0
Summary: Image processing tools with Cython acceleration
Author: Lee Denaro
License: MIT
License-File: LICENSE
Requires-Dist: numpy==2.2.0
Requires-Dist: opencv-python
Requires-Dist: cython
Dynamic: license-file
